claim/__init__.py
claim/admin.py
claim/apps.py
claim/gql_mutations.py
claim/gql_queries.py
claim/models.py
claim/report.py
claim/schema.py
claim/services.py
claim/subqueries.py
claim/test_helpers.py
claim/urls.py
claim/utils.py
claim/validations.py
claim/views.py
claim/attachment_strategies/__init__.py
claim/attachment_strategies/handle_claimdoc_attachment.py
claim/management/__init__.py
claim/management/commands/__init__.py
claim/management/commands/generateclaimadmins.py
claim/management/commands/generateclaims.py
claim/migrations/0001_initial.py
claim/migrations/0002_batchrun.py
claim/migrations/0003_claimofficer.py
claim/migrations/0004_claimattachment.py
claim/migrations/0005_claimmutation.py
claim/migrations/0006_claimattachment_url.py
claim/migrations/0007_auto_20200318_1443.py
claim/migrations/0008_create_claim_attachments_count_view.py
claim/migrations/0009_auto_20200421_1657.py
claim/migrations/0010_auto_20200611_0601.py
claim/migrations/0011_auto_20201126_1244.py
claim/migrations/0012_item_service_jsonExtField.py
claim/migrations/0013_feedbackprompt.py
claim/migrations/0014_change_code_limit.py
claim/migrations/0015_prohibit_interaction_for_enrolment_officer.py
claim/migrations/0016_update_django_scheme_with_missing_fields.py
claim/migrations/0017_set_managed_to_true.py
claim/migrations/0018_alter_jsonext_column.py
claim/migrations/0019_auto_20230615_1055.py
claim/migrations/0020_alter_claim_code.py
claim/migrations/0021_auto_20230818_0914.py
claim/migrations/0022_alter_feedbackprompt_phone_number.py
claim/migrations/0023_claim_restore.py
claim/migrations/0024_add_claim_restore_perms.py
claim/migrations/0025_auto_20231205_1455.py
claim/migrations/0026_add_sequences.py
claim/migrations/0027_auto_20240203_2339.py
claim/migrations/0028_claimattachmenttype_claimattachment_predefined_type.py
claim/migrations/0028_claimserviceitem_claimserviceservice.py
claim/migrations/0029_rename_pcpdate_claimserviceitem_created_date_and_more.py
openimis_be_claim-1.10.0.dist-info/licenses/LICENSE.md
openimis_be_claim-1.10.0.dist-info/METADATA
openimis_be_claim-1.10.0.dist-info/WHEEL
openimis_be_claim-1.10.0.dist-info/top_level.txt
openimis_be_claim-1.10.0.dist-info/RECORD
